Codificador/codificadorbcd.v
module codificadorbcd(BCD, S);

    input [3:0] BCD;
    output reg [6:0] S;

    always @ (BCD) begin
        case(BCD)
            4'b0000: S = 7'b1111110;
            4'b0001: S = 7'b0110000;
            4'b0010: S = 7'b1101101;
            4'b0011: S = 7'b1111001;
            4'b0100: S = 7'b0110011;
            4'b0101: S = 7'b1011011;
            4'b0110: S = 7'b1011111;
            4'b0111: S = 7'b1110000;
            4'b1000: S = 7'b1111111;
            4'b1001: S = 7'b1111011;
            4'b1010: S = 7'b1110111;
            4'b1011: S = 7'b0011111;
            4'b1100: S = 7'b1001110;
            4'b1101: S = 7'b0111101;
            4'b1110: S = 7'b1001111;
            4'b1111: S = 7'b1000111;
            default: S = 7'b0000000;
        endcase
    end

endmodule

Codificador/codificadorbcd_tb.v
`timescale 1ns/1ns
`include "codificadorbcd.v"

module codificadorbcd_tb;

    reg [3:0] BCD;
    wire [6:0] S;

    codificadorbcd uut(BCD, S);

    initial begin
        $dumpfile("codificadorbcd_tb.vcd");
        $dumpvars(0, codificadorbcd_tb);

        BCD = 4'b0000; #20
        BCD = 4'b0001; #20
        BCD = 4'b0010; #20
        BCD = 4'b0011; #20
        BCD = 4'b0100; #20
        BCD = 4'b0101; #20
        BCD = 4'b0110; #20
        BCD = 4'b0111; #20
        BCD = 4'b1000; #20
        BCD = 4'b1001; #20
        BCD = 4'b1010; #20
        BCD = 4'b1011; #20
        BCD = 4'b1100; #20
        BCD = 4'b1101; #20
        BCD = 4'b1110; #20
        BCD = 4'b1111; #20
        
        $display("Teste completo");
    end

endmodule

Codificador/codificadorbcd_tb.vcd
$date
	Mon Sep 23 09:07:48 2024
$end
$version
	Icarus Verilog
$end
$timescale
	1ns
$end
$scope module codificadorbcd_tb $end
$var wire 7 ! S [6:0] $end
$var reg 4 " BCD [3:0] $end
$scope module uut $end
$var wire 4 # BCD [3:0] $end
$var reg 7 $ S [6:0] $end
$upscope $end
$upscope $end
$enddefinitions $end
$comment Show the parameter values. $end
$dumpall
$end
#0
$dumpvars
b1111110 $
b0 #
b0 "
b1111110 !
$end
#20
b110000 !
b110000 $
b1 "
b1 #
#40
b1101101 !
b1101101 $
b10 "
b10 #
#60
b1111001 !
b1111001 $
b11 "
b11 #
#80
b110011 !
b110011 $
b100 "
b100 #
#100
b1011011 !
b1011011 $
b101 "
b101 #
#120
b1011111 !
b1011111 $
b110 "
b110 #
#140
b1110000 !
b1110000 $
b111 "
b111 #
#160
b1111111 !
b1111111 $
b1000 "
b1000 #
#180
b1111011 !
b1111011 $
b1001 "
b1001 #
#200
b1110111 !
b1110111 $
b1010 "
b1010 #
#220
b11111 !
b11111 $
b1011 "
b1011 #
#240
b1001110 !
b1001110 $
b1100 "
b1100 #
#260
b111101 !
b111101 $
b1101 "
b1101 #
#280
b1001111 !
b1001111 $
b1110 "
b1110 #
#300
b1000111 !
b1000111 $
b1111 "
b1111 #
