Decodificador/decodificadorbcd.v
module decodificadorbcd(A, enable, S);

    input [2:0] A;
    input enable;
    output reg [7:0] S;

    always @ (A) begin
        if (enable == 1)
            case(A)
                3'b000: S = 8'b00000001;
                3'b001: S = 8'b00000010;
                3'b010: S = 8'b00000100;
                3'b011: S = 8'b00001000;
                3'b100: S = 8'b00010000;
                3'b101: S = 8'b00100000;
                3'b110: S = 8'b01000000;
                3'b111: S = 8'b10000000;
                default: S = 8'b00000000;
            endcase
        else
            S = 8'b00000000;
    end

endmodule

Decodificador/decodificadorbcd_tb.v
`timescale 1ns/1ns
`include "decodificadorbcd.v"

module decodificadorbcd_tb;

    reg [2:0] A;
    reg enable;
    wire [7:0] S;

    decodificadorbcd uut(A, enable, S);

    initial begin
        $dumpfile("decodificadorbcd_tb.vcd");
        $dumpvars(0, decodificadorbcd_tb);
        enable = 1;
        A = 3'b000; #20
        A = 3'b001; #20
        A = 3'b010; #20
        A = 3'b011; #20
        A = 3'b100; #20
        A = 3'b101; #20
        A = 3'b110; #20
        A = 3'b111; #20
        enable = 0; #20
        $display("Teste completo");
    end

endmodule

Decodificador/decodificadorbcd_tb.vcd
$date
	Mon Sep 23 09:44:33 2024
$end
$version
	Icarus Verilog
$end
$timescale
	1ns
$end
$scope module decodificadorbcd_tb $end
$var wire 8 ! S [7:0] $end
$var reg 3 " A [2:0] $end
$var reg 1 # enable $end
$scope module uut $end
$var wire 3 $ A [2:0] $end
$var wire 1 # enable $end
$var reg 8 % S [7:0] $end
$upscope $end
$upscope $end
$enddefinitions $end
$comment Show the parameter values. $end
$dumpall
$end
#0
$dumpvars
b1 %
b0 $
1#
b0 "
b1 !
$end
#20
b10 !
b10 %
b1 "
b1 $
#40
b100 !
b100 %
b10 "
b10 $
#60
b1000 !
b1000 %
b11 "
b11 $
#80
b10000 !
b10000 %
b100 "
b100 $
#100
b100000 !
b100000 %
b101 "
b101 $
#120
b1000000 !
b1000000 %
b110 "
b110 $
#140
b10000000 !
b10000000 %
b111 "
b111 $
#160
0#
